anaphora/__init__.py
anaphora/__pycache__/__init__.cpython-36.pyc
pandas_anaphora-0.1b0.dist-info/METADATA
pandas_anaphora-0.1b0.dist-info/RECORD
pandas_anaphora-0.1b0.dist-info/WHEEL
pandas_anaphora-0.1b0.dist-info/top_level.txt
