Metadata-Version: 2.1
Name: pandas-anaphora
Version: 0.1b0
Summary: Anaphoric functions for columns in Pandas data frames
Home-page: https://github.com/gwerbin/pandas-anaphora
Author: Gregory Werbin
Author-email: outthere@me.gregwerbin.com
License: MIT
Project-URL: Bug Tracker, https://github.com/gwerbin/pandas-anaphora/issues
Project-URL: Documentation, https://github.com/gwerbin/pandas-anaphora/blob/master/README.md
Project-URL: Source Code, https://github.com/gwerbin/pandas-anaphora
Platform: UNKNOWN
Requires-Python: >= 3.4
Requires-Dist: setuptools
Requires-Dist: pandas (>=0.20)
Requires-Dist: toolz (>=0.9)
